pastebinpy/__init__.py
pastebinpy-0.1.5.dist-info/WHEEL
pastebinpy-0.1.5.dist-info/METADATA
pastebinpy-0.1.5.dist-info/RECORD
