Metadata-Version: 2.1
Name: pastebinpy
Version: 0.1.5
Summary: A Pastebin api created in python with easy to use syntax
License: MIT
Author: Cesiyi
Author-email: css@amogus.cloud
Maintainer: Cesiyi
Maintainer-email: css@amogus.cloud
Requires-Python: >=3.8,<4.0
Classifier: License :: OSI Approved :: MIT License
Classifier: Programming Language :: Python :: 3
Classifier: Programming Language :: Python :: 3.10
Classifier: Programming Language :: Python :: 3.8
Classifier: Programming Language :: Python :: 3.9
